django_starter/__init__.py
django_starter/cli.py
django_starter-0.5.0.dist-info/LICENSE
django_starter-0.5.0.dist-info/METADATA
django_starter-0.5.0.dist-info/WHEEL
django_starter-0.5.0.dist-info/entry_points.txt
django_starter-0.5.0.dist-info/top_level.txt
django_starter-0.5.0.dist-info/RECORD
